Metadata-Version: 2.1
Name: odoo13-addon-contract-sale
Version: 13.0.1.1.0
Summary: Contract from Sale
Home-page: https://github.com/OCA/contract
Author: Tecnativa, Odoo Community Association (OCA)
Author-email: support@odoo-community.org
License: AGPL-3
Platform: UNKNOWN
Classifier: Programming Language :: Python
Classifier: Framework :: Odoo
Classifier: License :: OSI Approved :: GNU Affero General Public License v3
Classifier: Development Status :: 5 - Production/Stable
Requires-Python: >=3.5
Requires-Dist: odoo13-addon-contract
Requires-Dist: odoo (<13.1dev,>=13.0a)
